saya/Deprecated.py
saya/StartThread.py
saya/__init__.py
saya/AVK/ALongPoll.py
saya/AVK/AStreamingAPI.py
saya/AVK/AUploader.py
saya/AVK/AVk.py
saya/AVK/__init__.py
saya/VK/Button.py
saya/VK/Event.py
saya/VK/Keyboard.py
saya/VK/LongPoll.py
saya/VK/StreamingAPI.py
saya/VK/Template.py
saya/VK/TemplateElement.py
saya/VK/Uploader.py
saya/VK/Vk.py
saya/VK/VkAuthManager.py
saya/VK/VkScript.py
saya/VK/__init__.py
saya-0.3.10.dist-info/LICENSE
saya-0.3.10.dist-info/METADATA
saya-0.3.10.dist-info/WHEEL
saya-0.3.10.dist-info/top_level.txt
saya-0.3.10.dist-info/RECORD
