Metadata-Version: 2.1
Name: saya
Version: 0.3.10
Summary: The framework for vk
Home-page: https://github.com/Ethosa/saya
Author: Ethosa
Author-email: social.ethosa@gmail.com
License: LGPLv3
Project-URL: Github, https://github.com/Ethosa/saya
Project-URL: Documentation, https://github.com/Ethosa/saya/blob/master/README.md
Keywords: vk api framework python
Platform: UNKNOWN
Classifier: Development Status :: 4 - Beta
Classifier: Programming Language :: Python :: 3
Classifier: Programming Language :: Python :: 3.4
Classifier: Programming Language :: Python :: 3.5
Classifier: Programming Language :: Python :: 3.6
Classifier: Programming Language :: Python :: 3.7
Classifier: License :: OSI Approved :: GNU Lesser General Public License v3 (LGPLv3)
Classifier: Operating System :: OS Independent
Requires-Python: >=3
Requires-Dist: requests
Requires-Dist: regex
Requires-Dist: beautifulsoup4
Requires-Dist: retranslator
Requires-Dist: websocket-client
Requires-Dist: aiohttp
